{"trial_id": "08", "hyperparameters": {"space": [{"class_name": "Int", "config": {"name": "num_layers", "default": null, "conditions": [], "min_value": 2, "max_value": 3, "step": 1, "sampling": "linear"}}, {"class_name": "Int", "config": {"name": "units_0", "default": null, "conditions": [], "min_value": 64, "max_value": 512, "step": 32, "sampling": "linear"}}, {"class_name": "Int", "config": {"name": "units_1", "default": null, "conditions": [], "min_value": 64, "max_value": 512, "step": 32, "sampling": "linear"}}, {"class_name": "Boolean", "config": {"name": "dropout", "default": false, "conditions": []}}, {"class_name": "Int", "config": {"name": "units_2", "default": null, "conditions": [], "min_value": 64, "max_value": 512, "step": 32, "sampling": "linear"}}], "values": {"num_layers": 3, "units_0": 96, "units_1": 416, "dropout": false, "units_2": 256}}, "metrics": {"metrics": {"loss": {"direction": "min", "observations": [{"value": [0.04719668719917536], "step": 38}]}, "accuracy": {"direction": "max", "observations": [{"value": [0.985456645488739], "step": 38}]}, "val_loss": {"direction": "min", "observations": [{"value": [0.38891714811325073], "step": 38}]}, "val_accuracy": {"direction": "max", "observations": [{"value": [0.9623287618160248], "step": 38}]}}}, "score": 0.9623287618160248, "best_step": 38, "status": "COMPLETED", "message": null}